Metadata-Version: 2.1
Name: apa102-gpiod
Version: 0.1.2
Summary: apa102 driver using userspace gpio character device through libgpiod
Home-page: http://github.com/shenghaoyang/apa102_gpiod
Author: Shenghao Yang
Author-email: me@shenghaoyang.info
License: MIT
Platform: UNKNOWN
Classifier: Development Status :: 4 - Beta
Classifier: License :: OSI Approved :: MIT License
Classifier: Programming Language :: Python :: 3.6
Classifier: Topic :: Software Development :: Libraries
Requires-Python: >=3.6, <4
